LICENSE
MANIFEST.in
README.txt
setup.py
OASYS1_COMSYL.egg-info/PKG-INFO
OASYS1_COMSYL.egg-info/SOURCES.txt
OASYS1_COMSYL.egg-info/dependency_links.txt
OASYS1_COMSYL.egg-info/entry_points.txt
OASYS1_COMSYL.egg-info/namespace_packages.txt
OASYS1_COMSYL.egg-info/not-zip-safe
OASYS1_COMSYL.egg-info/requires.txt
OASYS1_COMSYL.egg-info/top_level.txt
orangecontrib/__init__.py
orangecontrib/comsyl/__init__.py
orangecontrib/comsyl/scripts/AF_to_h5.py
orangecontrib/comsyl/scripts/create_widget.py
orangecontrib/comsyl/scripts/functions1D.py
orangecontrib/comsyl/scripts/h5view.py
orangecontrib/comsyl/scripts/load_results_from_file.py
orangecontrib/comsyl/scripts/test_import.py
orangecontrib/comsyl/util/__init__.py
orangecontrib/comsyl/util/light_source.py
orangecontrib/comsyl/util/messages.py
orangecontrib/comsyl/util/preprocessor.py
orangecontrib/comsyl/util/python_script.py
orangecontrib/comsyl/util/tally2d.py
orangecontrib/comsyl/widgets/__init__.py
orangecontrib/comsyl/widgets/applications/__init__.py
orangecontrib/comsyl/widgets/applications/comsyl_modes_loader.py
orangecontrib/comsyl/widgets/applications/comsyl_modes_selector.py
orangecontrib/comsyl/widgets/applications/comsyl_propagate_beamline.py
orangecontrib/comsyl/widgets/applications/ow_propagate_2d_modes_python_script.py
orangecontrib/comsyl/widgets/applications/icons/AFViewer.png
orangecontrib/comsyl/widgets/applications/icons/loader.png
orangecontrib/comsyl/widgets/applications/icons/propagator.png
orangecontrib/comsyl/widgets/applications/icons/selector.png
orangecontrib/comsyl/widgets/gui/__init__.py
orangecontrib/comsyl/widgets/gui/ow_comsyl_widget.py
orangecontrib/comsyl/widgets/tools/__init__.py
orangecontrib/comsyl/widgets/tools/comsyl_modes_file_reader.py
orangecontrib/comsyl/widgets/tools/comsyl_modes_file_writer.py
orangecontrib/comsyl/widgets/tools/icons/file_reader.png
orangecontrib/comsyl/widgets/tools/icons/file_writer.png
orangecontrib/comsyl/widgets/tools/icons/util.png